fetchv2_mcp_server/__init__.py
fetchv2_mcp_server/__main__.py
fetchv2_mcp_server/py.typed
fetchv2_mcp_server/server.py
fetchv2_mcp_server-1.1.0.dist-info/METADATA
fetchv2_mcp_server-1.1.0.dist-info/WHEEL
fetchv2_mcp_server-1.1.0.dist-info/entry_points.txt
fetchv2_mcp_server-1.1.0.dist-info/licenses/LICENSE
fetchv2_mcp_server-1.1.0.dist-info/RECORD
