Metadata-Version: 2.4
Name: fetchv2-mcp-server
Version: 1.1.0
Summary: A robust MCP server for fetching and extracting web content using Trafilatura
Project-URL: Homepage, https://github.com/praveenc/fetchv2-mcp-server
Project-URL: Repository, https://github.com/praveenc/fetchv2-mcp-server
Project-URL: Issues, https://github.com/praveenc/fetchv2-mcp-server/issues
Project-URL: Changelog, https://github.com/praveenc/fetchv2-mcp-server/blob/main/CHANGELOG.md
Author-email: Praveen Chamarthi <1090396+praveenc@users.noreply.github.com>
License: MIT
License-File: LICENSE
Keywords: ai-agent,content-extraction,llm,markdown,mcp,model-context-protocol,trafilatura,web-fetcher,web-scraping
Classifier: Development Status :: 4 - Beta
Classifier: Intended Audience :: Developers
Classifier: License :: OSI Approved :: MIT License
Classifier: Programming Language :: Python :: 3
Classifier: Programming Language :: Python :: 3.10
Classifier: Programming Language :: Python :: 3.11
Classifier: Programming Language :: Python :: 3.12
Classifier: Programming Language :: Python :: 3.13
Classifier: Topic :: Internet :: WWW/HTTP
Classifier: Topic :: Text Processing :: Markup :: Markdown
Classifier: Typing :: Typed
Requires-Python: >=3.10
Requires-Dist: defusedxml>=0.7.1
Requires-Dist: httpx>=0.27.0
Requires-Dist: mcp[cli]>=1.1.3
Requires-Dist: protego>=0.3.1
Requires-Dist: pydantic>=2.0.0
Requires-Dist: trafilatura>=2.0.0
